<?xml version="1.0" encoding="UTF-8"?>
<autorizacion>
<estado>AUTORIZADO</estado>
<numeroAutorizacion>0702201701200100100000607917926917452</numeroAutorizacion>
<fechaAutorizacion class="fechaAutorizacion">20170207</fechaAutorizacion>
<comprobante><![CDATA[<?xml version="1.0" encoding="UTF-8"?>
<factura id="comprobante" version="1.0.0">
<infoTributaria>
<ambiente>2</ambiente>
<tipoEmision>1</tipoEmision>
<razonSocial>COENPI</razonSocial>
<nombreComercial>MEGALUNCH</nombreComercial>
<ruc>1792691745001</ruc>
<claveAcceso>0702201701179269174500120010010000060790000607912</claveAcceso>
<codDoc>01</codDoc>
<estab>001</estab>
<ptoEmi>001</ptoEmi>
<secuencial>000006079</secuencial>
<dirMatriz>6 DE DICIEMBRE SN Y GRANADOS</dirMatriz>
</infoTributaria>
<infoFactura>
<fechaEmision>07/02/2017</fechaEmision>
<dirEstablecimiento>GRANADOS Y DE LAS HIEDRAS</dirEstablecimiento>
<obligadoContabilidad>NO</obligadoContabilidad>
<tipoIdentificacionComprador>05</tipoIdentificacionComprador>
<razonSocialComprador>MIGUEL ORQUERA</razonSocialComprador>
<identificacionComprador>1000982882</identificacionComprador>
<totalSinImpuestos>9.87</totalSinImpuestos>
<totalDescuento>0</totalDescuento>
<totalConImpuestos>
<totalImpuesto>
<codigo>2</codigo>
<codigoPorcentaje>3</codigoPorcentaje>
<baseImponible>9.87</baseImponible>
<valor>1.38</valor>
</totalImpuesto>
</totalConImpuestos>
<propina>0</propina>
<importeTotal>11.25</importeTotal>
<moneda>DOLAR</moneda>
<pagos>
<pago>
<formaPago>01</formaPago>
<total>     11.25</total>
</pago>
</pagos>
</infoFactura>
<detalles>
<detalle>
<codigoPrincipal>0101167</codigoPrincipal>
<descripcion>INVITADO 1</descripcion>
<cantidad>1</cantidad>
<precioUnitario>0</precioUnitario>
<descuento>0</descuento>
<precioTotalSinImpuesto>0</precioTotalSinImpuesto>
<impuestos>
<impuesto>
<codigo>2</codigo>
<codigoPorcentaje>3</codigoPorcentaje>
<tarifa>14</tarifa>
<baseImponible>0</baseImponible>
<valor>0</valor>
</impuesto>
</impuestos>
</detalle>
<detalle>
<codigoPrincipal>0105001</codigoPrincipal>
<descripcion>MNB  CARNE Y FREJOL</descripcion>
<cantidad>1</cantidad>
<precioUnitario>4.82</precioUnitario>
<descuento>0</descuento>
<precioTotalSinImpuesto>4.82</precioTotalSinImpuesto>
<impuestos>
<impuesto>
<codigo>2</codigo>
<codigoPorcentaje>3</codigoPorcentaje>
<tarifa>14</tarifa>
<baseImponible>4.82</baseImponible>
<valor>0.68</valor>
</impuesto>
</impuestos>
</detalle>
<detalle>
<codigoPrincipal>0107001</codigoPrincipal>
<descripcion>GUAYACO DE CARNE</descripcion>
<cantidad>1</cantidad>
<precioUnitario>5.04</precioUnitario>
<descuento>0</descuento>
<precioTotalSinImpuesto>5.04</precioTotalSinImpuesto>
<impuestos>
<impuesto>
<codigo>2</codigo>
<codigoPorcentaje>3</codigoPorcentaje>
<tarifa>14</tarifa>
<baseImponible>5.04</baseImponible>
<valor>0.71</valor>
</impuesto>
</impuestos>
</detalle>
</detalles>
<infoAdicional>
<campoAdicional nombre="Direccion">CENTRO QUITO</campoAdicional>
<campoAdicional nombre="EmaiL">miguelo42 hotmail com</campoAdicional>
<campoAdicional nombre="NumDocumento">FR0005421A-0301-M</campoAdicional>
</infoAdicional>
<ds:Signature xmlns:ds="http://www.w3.org/2000/09/xmldsig#" Id="Signature873747" xmlns:etsi="http://uri.etsi.org/01903/v1.3.2#">
<ds:SignedInfo Id="Signature-SignedInfo695981">
<ds:CanonicalizationMethod Algorithm="http://www.w3.org/TR/2001/REC-xml-c14n-20010315"/>
<ds:SignatureMethod Algorithm="http://www.w3.org/2000/09/xmldsig#rsa-sha1"/>
<ds:Reference Id="SignedPropertiesID108491" Type="http://uri.etsi.org/01903#SignedProperties" URI="#Signature873747-SignedProperties384424">
<ds:DigestMethod Algorithm="http://www.w3.org/2000/09/xmldsig#sha1"/>
<ds:DigestValue>BMjAi46XNfBD6wRm0MxZeJVFXcM=</ds:DigestValue>
</ds:Reference>
<ds:Reference URI="#Certificate1806241">
<ds:DigestMethod Algorithm="http://www.w3.org/2000/09/xmldsig#sha1"/>
<ds:DigestValue>33F7S9odMmMtTnowxQhbWP8mIho=</ds:DigestValue>
</ds:Reference>
<ds:Reference Id="Reference-ID-526186" URI="#comprobante">
<ds:Transforms>
<ds:Transform Algorithm="http://www.w3.org/2000/09/xmldsig#enveloped-signature"/>
</ds:Transforms>
<ds:DigestMethod Algorithm="http://www.w3.org/2000/09/xmldsig#sha1"/>
<ds:DigestValue>R7kmYyFMr/wbtTsnfd+EdXjbIJ0=</ds:DigestValue>
</ds:Reference>
</ds:SignedInfo>
<ds:SignatureValue Id="SignatureValue726131">
ZmprkGiqSb7xDqnz/cVKb4JeDlHpG47Tt34VTGztShVK/sFpg6xWH6z+VI+OfBVUvC1929BoCmrk
tLkHK1r3jUP/D2REIo7kX+C4iWtSoc6gZZwfLuK2NDfeb33bWHr1QzJxbyEJ3Mj0MQAGBMeo3Rf+
eJEhyK3Zkxu9kDOQ/wkN2MCBo+HiEEBdlXWCxv02zpBk7TsUSs2oZJUZnwa79P0eyIfXolEDH/PP
BopWCIvx4Cc3LmSz6jrnkvq/dTdyoFXjj2aLobSKk6vJ3TYaIwoeOh5pN3nLHdAQhgB/eg3mybuj
L6dT0hJVWENr9tn4S7wtSpvIqY+avUgEJ4b+jQ==
</ds:SignatureValue>
<ds:KeyInfo Id="Certificate1806241">
<ds:X509Data>
<ds:X509Certificate>
MIIJSzCCBzOgAwIBAgIETkb75TANBgkqhkiG9w0BAQsFADCBoTELMAkGA1UEBhMCRUMxIjAgBgNV
BAoTGUJBTkNPIENFTlRSQUwgREVMIEVDVUFET1IxNzA1BgNVBAsTLkVOVElEQUQgREUgQ0VSVElG
SUNBQ0lPTiBERSBJTkZPUk1BQ0lPTi1FQ0lCQ0UxDjAMBgNVBAcTBVFVSVRPMSUwIwYDVQQDExxB
QyBCQU5DTyBDRU5UUkFMIERFTCBFQ1VBRE9SMB4XDTE2MDgxOTE0NDgzNVoXDTE4MDgxOTE1MTgz
NVowgbIxCzAJBgNVBAYTAkVDMSIwIAYDVQQKExlCQU5DTyBDRU5UUkFMIERFTCBFQ1VBRE9SMTcw
NQYDVQQLEy5FTlRJREFEIERFIENFUlRJRklDQUNJT04gREUgSU5GT1JNQUNJT04tRUNJQkNFMQ4w
DAYDVQQHEwVRVUlUTzE2MBEGA1UEBRMKMDAwMDE3MjQwNjAhBgNVBAMTGlBBQkxPIFJPTUFOIFBJ
TkVEQSBWQUxMRUpPMIIBIjANBgkqhkiG9w0BAQEFAAOCAQ8AMIIBCgKCAQEAv9szbrEt0LSMFj2D
aZQ9UVMvr+zBGaAdR4jhge4s+sqzm2KYCKcbM3qnyEJzjBjbGN1Y2XMdma0Rq1KL7gVuTkqs6IXb
WjuUv+7yr4PPNjZx3EqcYbVQXfG4pHgeDHDirc+CxVkE7AQ0y+AZBxcItiprdPyxgKLANvU4h72o
gs5BnHkDv768MSRQzcbgGfF6yvd1JQo4sE0+HOcLCt/hLgnJY0v50garZZCnbIyt4Fl4E5XjKdLH
UUtXJyVlGKjcg4ypdPBcCYabKbSXC3bIzHf6cszSQcDoDvMJISeuAjEoEmdUM5GrnxW2v6JVBa9l
GNEz4pvSdzskgSbx/BcZgQIDAQABo4IEdjCCBHIwCwYDVR0PBAQDAgUgMIGRBggrBgEFBQcBAQSB
hDCBgTA+BggrBgEFBQcwAYYyaHR0cDovL29jc3AuZWNpLmJjZS5lYy9lamJjYS9wdWJsaWN3ZWIv
c3RhdHVzL29jc3AwPwYIKwYBBQUHMAGGM2h0dHA6Ly9vY3NwMS5lY2kuYmNlLmVjL2VqYmNhL3B1
YmxpY3dlYi9zdGF0dXMvb2NzcDAWBgorBgEEAYKoOwMKBAgTBkNPRU5QSTAdBgorBgEEAYKoOwML
BA8TDTE3OTI2OTE3NDUwMDEwGgYKKwYBBAGCqDsDAQQMEwoxNzE5NTA0MDAxMBsGCisGAQQBgqg7
AwIEDRMLUEFCTE8gUk9NQU4wFgYKKwYBBAGCqDsDAwQIEwZQSU5FREEwFwYKKwYBBAGCqDsDBAQJ
EwdWQUxMRUpPMB8GCisGAQQBgqg7AwUEERMPR0VSRU5URSBHRU5FUkFMMDMGCisGAQQBgqg7AwcE
JRMjQVYgREUgTE9TIEdSQU5BRE9TIFkgREUgTEFTIEhJRURSQVMwGQYKKwYBBAGCqDsDCAQLEwkw
MjIyNjI2NDEwFQYKKwYBBAGCqDsDCQQHEwVRdWl0bzAXBgorBgEEAYKoOwMMBAkTB0VDVUFET1Iw
IAYKKwYBBAGCqDsDMwQSExBTT0ZUV0FSRS1BUkNISVZPMCIGA1UdEQQbMBmBF2NvZW5waWNpYWx0
ZGFAZ21haWwuY29tMIIB3wYDVR0fBIIB1jCCAdIwggHOoIIByqCCAcaGgdVsZGFwOi8vYmNlcWxk
YXBzdWJwMS5iY2UuZWMvY249Q1JMMzUyLGNuPUFDJTIwQkFOQ08lMjBDRU5UUkFMJTIwREVMJTIw
RUNVQURPUixsPVFVSVRPLG91PUVOVElEQUQlMjBERSUyMENFUlRJRklDQUNJT04lMjBERSUyMElO
Rk9STUFDSU9OLUVDSUJDRSxvPUJBTkNPJTIwQ0VOVFJBTCUyMERFTCUyMEVDVUFET1IsYz1FQz9j
ZXJ0aWZpY2F0ZVJldm9jYXRpb25MaXN0P2Jhc2WGNGh0dHA6Ly93d3cuZWNpLmJjZS5lYy9DUkwv
ZWNpX2JjZV9lY19jcmxmaWxlY29tYi5jcmykgbUwgbIxCzAJBgNVBAYTAkVDMSIwIAYDVQQKExlC
QU5DTyBDRU5UUkFMIERFTCBFQ1VBRE9SMTcwNQYDVQQLEy5FTlRJREFEIERFIENFUlRJRklDQUNJ
T04gREUgSU5GT1JNQUNJT04tRUNJQkNFMQ4wDAYDVQQHEwVRVUlUTzElMCMGA1UEAxMcQUMgQkFO
Q08gQ0VOVFJBTCBERUwgRUNVQURPUjEPMA0GA1UEAxMGQ1JMMzUyMB8GA1UdIwQYMBaAFBj58Pvm
MhyZZjkqyouyaX1JJ7/OMB0GA1UdDgQWBBRORzX2bR91PWPCrZaXwv8QJnYY4TAJBgNVHRMEAjAA
MBkGCSqGSIb2fQdBAAQMMAobBFY4LjEDAgSwMA0GCSqGSIb3DQEBCwUAA4ICAQAVnoRdXF8CtG3n
HFmvd0m3Im5JtB2G1bQyvsWWBgUi0SlpLoETTaqBairw6HqLZYcwpEkEGOed0fCtcuc1cWk8xXd+
ynIAmAl9bz8VgFQmR2B9qDAGPVm72aka7gI8QRyExCJjxfkS2YAaQ/nM2jnfGZmS8Iu+WWBlQ4Px
XDggRNDFAsstB6S+VuM8Q0CKha7qv97aDcLv7SW1LLMZUaHHX7nZPrcmFK7GFnf0EmW3j/HD+uS1
hmIOYTGx0QokApdhM0D/rZMgzQy6fFE1muEZzWYK0/9xnIB8I/Tg7/2T3AMdn8nLkoHHIazwLg8N
Ev6kcnKLUtkhRAsrq+TrBHgUsjd5ZIJDOIaly2l+EriNDmSAPVat2Ti/Or0nN7128Dli4dP8cZe5
b3COB4/dzKujP828WP5VWsrVpuIOLy2tnSbviIERma+I+VmzcSdg4xaImI49p+ymg1K75tSRt01e
wIsXP8uEV0Kss/2aihYhTxzTSw1/FV/LCZYXNSnGejvCPj1+zeOdxeoR+3u8oSEYw0IcMLVs1zJS
yIdbboAm1PTPnrFg5R/h9BAuLSostCcgth2rqyLRBF9GE+vfo4lWgzXj5LO4GyrJAj4c3kINIUtU
5wXPWBf1vUyNZ6Vn2BlYVRcSkOp+SgOxhRwfk0Rw079ks76yT1I/nYnm+kmc0w==
</ds:X509Certificate>
</ds:X509Data>
<ds:KeyValue>
<ds:RSAKeyValue>
<ds:Modulus>
v9szbrEt0LSMFj2DaZQ9UVMvr+zBGaAdR4jhge4s+sqzm2KYCKcbM3qnyEJzjBjbGN1Y2XMdma0R
q1KL7gVuTkqs6IXbWjuUv+7yr4PPNjZx3EqcYbVQXfG4pHgeDHDirc+CxVkE7AQ0y+AZBxcItipr
dPyxgKLANvU4h72ogs5BnHkDv768MSRQzcbgGfF6yvd1JQo4sE0+HOcLCt/hLgnJY0v50garZZCn
bIyt4Fl4E5XjKdLHUUtXJyVlGKjcg4ypdPBcCYabKbSXC3bIzHf6cszSQcDoDvMJISeuAjEoEmdU
M5GrnxW2v6JVBa9lGNEz4pvSdzskgSbx/BcZgQ==
</ds:Modulus>
<ds:Exponent>AQAB</ds:Exponent>
</ds:RSAKeyValue>
</ds:KeyValue>
</ds:KeyInfo>
<ds:Object Id="Signature873747-Object591412"><etsi:QualifyingProperties Target="#Signature873747"><etsi:SignedProperties Id="Signature873747-SignedProperties384424"><etsi:SignedSignatureProperties><etsi:SigningTime>2017-02-07T12:18:55-05:00</etsi:SigningTime><etsi:SigningCertificate><etsi:Cert><etsi:CertDigest><ds:DigestMethod Algorithm="http://www.w3.org/2000/09/xmldsig#sha1"/><ds:DigestValue>BJwq6IpQXEBXFQZzRfbMAF9+cSk=</ds:DigestValue></etsi:CertDigest><etsi:IssuerSerial><ds:X509IssuerName>CN=AC BANCO CENTRAL DEL ECUADOR,L=QUITO,OU=ENTIDAD DE CERTIFICACION DE INFORMACION-ECIBCE,O=BANCO CENTRAL DEL ECUADOR,C=EC</ds:X509IssuerName><ds:X509SerialNumber>1313274853</ds:X509SerialNumber></etsi:IssuerSerial></etsi:Cert></etsi:SigningCertificate></etsi:SignedSignatureProperties><etsi:SignedDataObjectProperties><etsi:DataObjectFormat ObjectReference="#Reference-ID-526186"><etsi:Description>contenido comprobante</etsi:Description><etsi:MimeType>text/xml</etsi:MimeType></etsi:DataObjectFormat></etsi:SignedDataObjectProperties></etsi:SignedProperties></etsi:QualifyingProperties></ds:Object></ds:Signature></factura>]]>
</comprobante>
<mensajes>
<mensaje>
<mensaje>
<identificador></identificador>
<mensaje></mensaje>
<tipo></tipo>
<InformacionAdicional></InformacionAdicional>
</mensaje>
</mensaje>
</mensajes>
</autorizacion>